odoo/addons/product_state/README.rst
odoo/addons/product_state/__init__.py
odoo/addons/product_state/__manifest__.py
odoo/addons/product_state/data/product_state_data.xml
odoo/addons/product_state/i18n/ca.po
odoo/addons/product_state/i18n/de.po
odoo/addons/product_state/i18n/es.po
odoo/addons/product_state/i18n/fr.po
odoo/addons/product_state/i18n/hr.po
odoo/addons/product_state/i18n/it.po
odoo/addons/product_state/i18n/nl.po
odoo/addons/product_state/i18n/nl_NL.po
odoo/addons/product_state/i18n/product_state.pot
odoo/addons/product_state/i18n/pt.po
odoo/addons/product_state/i18n/sl.po
odoo/addons/product_state/models/__init__.py
odoo/addons/product_state/models/product_state.py
odoo/addons/product_state/models/product_template.py
odoo/addons/product_state/readme/CONTRIBUTORS.md
odoo/addons/product_state/readme/CREDITS.md
odoo/addons/product_state/readme/DESCRIPTION.md
odoo/addons/product_state/readme/USAGE.md
odoo/addons/product_state/security/ir.model.access.csv
odoo/addons/product_state/security/product_state_security.xml
odoo/addons/product_state/static/description/icon.png
odoo/addons/product_state/static/description/index.html
odoo/addons/product_state/tests/__init__.py
odoo/addons/product_state/tests/test_product_state.py
odoo/addons/product_state/views/product_state_views.xml
odoo/addons/product_state/views/product_template_views.xml
odoo_addon_product_state-18.0.1.0.0.7.dist-info/METADATA
odoo_addon_product_state-18.0.1.0.0.7.dist-info/WHEEL
odoo_addon_product_state-18.0.1.0.0.7.dist-info/top_level.txt
odoo_addon_product_state-18.0.1.0.0.7.dist-info/RECORD
